Metadata-Version: 1.0
Name: nwalign
Version: 0.3.0
Summary: Needleman-Wunsch global sequence alignment
Home-page: http://bitbucket.org/brentp/biostuff/
Author: brentp
Author-email: bpederse@gmail.com
License: BSD
Keywords: sequence bioinformatics alignment needleman-wunsch
Platform: UNKNOWN
Classifier: Development Status :: 3 - Alpha
Classifier: Intended Audience :: Developers
Classifier: Intended Audience :: Science/Research
Classifier: License :: OSI Approved :: BSD License
Classifier: Operating System :: OS Independent
Classifier: Programming Language :: Python
Classifier: Topic :: Scientific/Engineering :: Bio-Informatics
Classifier: Topic :: Scientific/Engineering
Classifier: Topic :: Text Processing
